main.py
setup.py
CascadeV.egg-info/PKG-INFO
CascadeV.egg-info/SOURCES.txt
CascadeV.egg-info/dependency_links.txt
CascadeV.egg-info/requires.txt
CascadeV.egg-info/top_level.txt